setup.cfg
setup.py
bin/stellator
stellator/__init__.py
stellator/config.py
stellator/constants.py
stellator/fileparser.py
stellator/inventory.py
stellator/util.py
stellator/virtualmachine.py
stellator/vmrun.py
stellator.egg-info/PKG-INFO
stellator.egg-info/SOURCES.txt
stellator.egg-info/dependency_links.txt
stellator.egg-info/requires.txt
stellator.egg-info/top_level.txt