Metadata-Version: 1.0
Name: stellator
Version: 1.0.5
Summary: Scripts to manage vmware fusion headless virtual machines
Home-page: https://github.com/hile/stellator/
Author: Ilkka Tuohela
Author-email: hile@iki.fi
License: PSF
Keywords: vmware fusion control scripts
Platform: UNKNOWN
